[{
  "version": "1.0",
  "image": {
    "name": "upload/df1c5df240b83fea3e28c4ea24989658f710eba9-p.png[0]",
    "baseName": "df1c5df240b83fea3e28c4ea24989658f710eba9-p.png",
    "format": "PNG",
    "formatDescription": "PNG",
    "mimeType": "image/png",
    "class": "DirectClass",
    "geometry": {
      "width": 794,
      "height": 1123,
      "x": 0,
      "y": 0
    },
    "units": "Undefined",
    "type": "TrueColorAlpha",
    "baseType": "Undefined",
    "endianness": "Undefined",
    "colorspace": "sRGB",
    "depth": 8,
    "baseDepth": 8,
    "channelDepth": {
      "alpha": 8,
      "red": 8,
      "green": 8,
      "blue": 8
    },
    "pixels": 3566648,
    "imageStatistics": {
      "Overall": {
        "min": 0,
        "max": 255,
        "mean": 39.384,
        "median": 0,
        "standardDeviation": 81.941,
        "kurtosis": 1.9125,
        "skewness": 1.9035,
        "entropy": 0.17094
      }
    },
    "channelStatistics": {
      "alpha": {
        "min": 0,
        "max": 255,
        "mean": 53.463,
        "median": 0,
        "standardDeviation": 103.17,
        "kurtosis": 0.048973,
        "skewness": 1.4264,
        "entropy": 0.11646
      },
      "red": {
        "min": 0,
        "max": 255,
        "mean": 46.598,
        "median": 0,
        "standardDeviation": 91.372,
        "kurtosis": 0.45142,
        "skewness": 1.524,
        "entropy": 0.18735
      },
      "green": {
        "min": 0,
        "max": 255,
        "mean": 26.898,
        "median": 0,
        "standardDeviation": 64.236,
        "kurtosis": 6.2704,
        "skewness": 2.6719,
        "entropy": 0.18975
      },
      "blue": {
        "min": 0,
        "max": 255,
        "mean": 30.578,
        "median": 0,
        "standardDeviation": 68.988,
        "kurtosis": 4.1956,
        "skewness": 2.3101,
        "entropy": 0.19019
      }
    },
    "alpha": "#00000000",
    "renderingIntent": "Perceptual",
    "gamma": 0.45455,
    "chromaticity": {
      "redPrimary": {
        "x": 0.64,
        "y": 0.33
      },
      "greenPrimary": {
        "x": 0.3,
        "y": 0.6
      },
      "bluePrimary": {
        "x": 0.15,
        "y": 0.06
      },
      "whitePrimary": {
        "x": 0.3127,
        "y": 0.329
      }
    },
    "matteColor": "#BDBDBD",
    "backgroundColor": "#FFFFFF",
    "borderColor": "#DFDFDF",
    "transparentColor": "#00000000",
    "interlace": "None",
    "intensity": "Undefined",
    "compose": "Over",
    "pageGeometry": {
      "width": 794,
      "height": 1123,
      "x": 0,
      "y": 0
    },
    "dispose": "Undefined",
    "iterations": 0,
    "compression": "Zip",
    "orientation": "Undefined",
    "properties": {
      "date:create": "2025-09-23T21:36:49+00:00",
      "date:modify": "2025-09-23T21:36:49+00:00",
      "date:timestamp": "2025-09-23T21:36:50+00:00",
      "png:bKGD": "chunk was found (see Background color, above)",
      "png:cHRM": "chunk was found (see Chromaticity, above)",
      "png:gAMA": "gamma=0.45455 (See Gamma, above)",
      "png:IHDR.bit-depth-orig": "8",
      "png:IHDR.bit_depth": "8",
      "png:IHDR.color-type-orig": "6",
      "png:IHDR.color_type": "6 (RGBA)",
      "png:IHDR.interlace_method": "0 (Not interlaced)",
      "png:IHDR.width,height": "794, 1123",
      "png:sRGB": "intent=0 (Perceptual Intent)",
      "png:text": "2 tEXt/zTXt/iTXt chunks were found",
      "signature": "1fa6ccf5d1c6d250261815c6805bd9cac538ead9029822e0478934d300b29bed"
    },
    "tainted": false,
    "filesize": "136.69KB",
    "numberPixels": "891.66K",
    "pixelsPerSecond": "32.192MB",
    "userTime": "0.040u",
    "elapsedTime": "0:01.027",
    "version": "ImageMagick 7.1.0-52 Q8 x86 04ee6ce:20221106 https://imagemagick.org"
  }
}]
